LICENSE
MANIFEST.in
README.rst
setup.py
django_graphene_gis_extension.egg-info/PKG-INFO
django_graphene_gis_extension.egg-info/SOURCES.txt
django_graphene_gis_extension.egg-info/dependency_links.txt
django_graphene_gis_extension.egg-info/requires.txt
django_graphene_gis_extension.egg-info/top_level.txt
graphene_gis_extension/__init__.py
graphene_gis_extension/apps.py
graphene_gis_extension/fields.py
graphene_gis_extension/input_types.py
graphene_gis_extension/scalars.py