Metadata-Version: 1.1
Name: django-graphene-gis-extension
Version: 0.2
Summary: A GIS extension for graphene-django that defines scalars, field conversions, and other useful things
Home-page: https://serioese.gmbh/
Author: Simon Welker
Author-email: simon@serioese.gmbh
License: MIT License
Platform: UNKNOWN
Classifier: Environment :: Web Environment
Classifier: Framework :: Django
Classifier: Framework :: Django :: 2.1
Classifier: Intended Audience :: Developers
Classifier: License :: OSI Approved :: MIT License
Classifier: Operating System :: OS Independent
Classifier: Programming Language :: Python
Classifier: Programming Language :: Python :: 3.5
Classifier: Programming Language :: Python :: 3.6
Classifier: Programming Language :: Python :: 3.7
Classifier: Topic :: Internet :: WWW/HTTP
Classifier: Topic :: Internet :: WWW/HTTP :: Dynamic Content
